replayenhancer/AdditionalParticipantPacket.py
replayenhancer/ParticipantPacket.py
replayenhancer/GTStandings.py
replayenhancer/replayenhancer.py
replayenhancer/SeriesStandingsWithChange.py
replayenhancer/__init__.py
replayenhancer/Packet.py
replayenhancer/DefaultCards.py
replayenhancer/RaceResultsWithChange.py
replayenhancer/packetcapture.py
replayenhancer/Track.py
replayenhancer/StaticBase.py
replayenhancer/RaceData.py
replayenhancer/TelemetryDataPacket.py
replayenhancer/lib/Roboto-Medium.ttf
replayenhancer/lib/Roboto-Regular.ttf
replayenhancer/lib/track_data.json
replayenhancer-0.6.dist-info/METADATA
replayenhancer-0.6.dist-info/WHEEL
replayenhancer-0.6.dist-info/DESCRIPTION.rst
replayenhancer-0.6.dist-info/RECORD
replayenhancer-0.6.dist-info/top_level.txt
replayenhancer-0.6.dist-info/metadata.json
replayenhancer-0.6.dist-info/entry_points.txt
test/test_RaceData.py
test/archive_TelemetryDataPacket.py
test/test_StaticBase.py
test/test_SeriesStandingsWithChange.py
test/test_packetcapture.py
test/test_AdditionalParticipantPacket.py
test/test_GTStandings.py
test/test_DefaultCards.py
test/__init__.py
test/test_RaceResultsWithChange.py
test/test_TelemetryDataPacket.py
test/test_ParticipantPacket.py
test/test_Track.py
