Metadata-Version: 2.0
Name: replayenhancer
Version: 0.6
Summary: Replay Enhancer 0.6
Home-page: https://github.com/SenorPez/project-cars-replay-enhancer
Author: Senor Pez
Author-email: contact_at_github@example.org
License: MIT
Keywords: gaming racing video data streaming
Platform: UNKNOWN
Classifier: Development Status :: 4 - Beta
Classifier: Intended Audience :: End Users/Desktop
Classifier: License :: OSI Approved :: MIT License
Classifier: Programming Language :: Python :: 3.3
Classifier: Programming Language :: Python :: 3.4
Classifier: Programming Language :: Python :: 3.5
Classifier: Programming Language :: Python :: 3.6
Classifier: Programming Language :: Python :: 3 :: Only
Requires-Dist: moviepy
Requires-Dist: natsort
Requires-Dist: Pillow
Requires-Dist: tqdm
Provides-Extra: dev
Provides-Extra: test
